tc_prometheus/__init__.py
tc_prometheus/metrics/__init__.py
tc_prometheus/metrics/prometheus_metrics.py
vows/__init__.py
vows/metrics_vows.py
dffrntlab_tc_prometheus-0.2.0.dist-info/LICENSE
dffrntlab_tc_prometheus-0.2.0.dist-info/METADATA
dffrntlab_tc_prometheus-0.2.0.dist-info/WHEEL
dffrntlab_tc_prometheus-0.2.0.dist-info/top_level.txt
dffrntlab_tc_prometheus-0.2.0.dist-info/RECORD
